xlsxslim.py
xlsxslim-2.0.2.dist-info/licenses/LICENSE
xlsxslim-2.0.2.dist-info/METADATA
xlsxslim-2.0.2.dist-info/WHEEL
xlsxslim-2.0.2.dist-info/entry_points.txt
xlsxslim-2.0.2.dist-info/top_level.txt
xlsxslim-2.0.2.dist-info/RECORD
