Metadata-Version: 2.4
Name: xlsxslim
Version: 2.0.2
Summary: Reduce Excel file size by removing empty rows, columns, and excess formatting
Author-email: "Vladyslav V. Prodan" <admin@support.od.ua>
License: BSD-3-Clause
Project-URL: Homepage, https://github.com/click0/xlsxslim
Project-URL: Repository, https://github.com/click0/xlsxslim
Project-URL: Issues, https://github.com/click0/xlsxslim/issues
Project-URL: Documentation, https://github.com/click0/xlsxslim#readme
Project-URL: Documentation (Українська), https://github.com/click0/xlsxslim/blob/main/README_uk.md
Project-URL: Changelog, https://github.com/click0/xlsxslim/releases
Keywords: excel,xlsx,optimize,compress,slim,reduce,filesize
Classifier: Development Status :: 4 - Beta
Classifier: Environment :: Console
Classifier: Intended Audience :: End Users/Desktop
Classifier: Intended Audience :: Developers
Classifier: License :: OSI Approved :: BSD License
Classifier: Operating System :: OS Independent
Classifier: Programming Language :: Python :: 3
Classifier: Programming Language :: Python :: 3.9
Classifier: Programming Language :: Python :: 3.10
Classifier: Programming Language :: Python :: 3.11
Classifier: Programming Language :: Python :: 3.12
Classifier: Programming Language :: Python :: 3.13
Classifier: Topic :: Office/Business :: Office Suites
Classifier: Topic :: Utilities
Requires-Python: >=3.9
License-File: LICENSE
Requires-Dist: click>=8.0.0
Requires-Dist: psutil>=5.9.0
Provides-Extra: dev
Requires-Dist: pytest>=7.0.0; extra == "dev"
Requires-Dist: pytest-cov>=4.0.0; extra == "dev"
Requires-Dist: openpyxl>=3.1.0; extra == "dev"
Dynamic: license-file
